py2latex/__init__.py
py2latex/core.py
py2latex/formatting.py
py2latex/glossaries.py
py2latex/markdown_parser.py
py2latex/mdx_latex.py
py2latex/sectioning.py
py2latex/tables.py
py2latex/templates.py
py2latex/templates/longtable.tex
py2latex/templates/main.tex
py2latex/templates/sectioning.tex
py2latex/templates/subtables.tex
py2latex/templates/table.tex
py2latex-0.0.6.dist-info/LICENSE
py2latex-0.0.6.dist-info/METADATA
py2latex-0.0.6.dist-info/WHEEL
py2latex-0.0.6.dist-info/entry_points.txt
py2latex-0.0.6.dist-info/top_level.txt
py2latex-0.0.6.dist-info/RECORD
