Metadata-Version: 2.1
Name: py2latex
Version: 0.0.6
Summary: Create LaTeX documents with Python, Markdown and Jinja2.
Home-page: https://github.com/domdfcoding/py2latex
Author: Dominic Davis-Foster
Author-email: dominic@davis-foster.co.uk
License: GNU Lesser General Public License v3 or later (LGPLv3+)
Project-URL: Documentation, https://py2latex.readthedocs.io
Project-URL: Issue Tracker, https://github.com/domdfcoding/py2latex/issues
Project-URL: Source Code, https://github.com/domdfcoding/py2latex
Platform: UNKNOWN
Classifier: Development Status :: 3 - Alpha
Classifier: Intended Audience :: Developers
Classifier: Operating System :: OS Independent
Classifier: Topic :: Utilities
Classifier: Programming Language :: Python :: 3.6
Classifier: Programming Language :: Python :: Implementation :: CPython
Classifier: Programming Language :: Python :: 3.7
Classifier: Programming Language :: Python :: 3.8
Classifier: Programming Language :: Python
Classifier: Programming Language :: Python :: 3 :: Only
Classifier: License :: OSI Approved :: GNU Lesser General Public License v3 or later (LGPLv3+)
Requires-Python: >=3.6
Requires-Dist: tabulate (>=0.8.7)
Requires-Dist: jinja2
Requires-Dist: markdown
Requires-Dist: PyYaml
Provides-Extra: all
